$
setup.py
lib/__init__.py
lib/ansy.py
lib/args.py
lib/atom.py
lib/bitbucket.py
lib/bower.py
lib/bytes.py
lib/check.py
lib/codebricks.py
lib/color.py
lib/config.py
lib/cpm.py
lib/cpplint.py
lib/cson.py
lib/css.py
lib/curl.py
lib/dict.py
lib/dir.py
lib/error.py
lib/file.py
lib/fn.py
lib/ftp.py
lib/ghbadges.py
lib/git.py
lib/github.py
lib/hg.py
lib/http.py
lib/input.py
lib/inspect.py
lib/iterator.py
lib/json.py
lib/kwargs.py
lib/list.py
lib/main.py
lib/make.py
lib/markdown.py
lib/npm.py
lib/orddir.py
lib/pacman.py
lib/predicate.py
lib/queue.py
lib/repo.py
lib/sak.py
lib/shieldsio.py
lib/site.py
lib/source.py
lib/str.py
lib/sys.py
lib/tex.py
lib/time.py
lib/url.py
lib/ver.py
lib/nice/__init__.py
lib/nice/file.py
lib/nice/ftp.py
sak/__init__.py
sak/apache.py
sak/atom.py
sak/beamer.py
sak/bitbucket.py
sak/bower.py
sak/cat.py
sak/clipboard.py
sak/codebricks.py
sak/codeclimate.py
sak/config.py
sak/contributions.py
sak/cpm.py
sak/cpp.py
sak/css.py
sak/date.py
sak/dotfiles.py
sak/git.py
sak/github.py
sak/gmail.py
sak/google.py
sak/help.py
sak/img.py
sak/iter.py
sak/js.py
sak/json.py
sak/navigator.py
sak/npm.py
sak/oeis.py
sak/orddir.py
sak/password.py
sak/pdf.py
sak/pip3.py
sak/queue.py
sak/sak.py
sak/site.py
sak/stream.py
sak/sty.py
sak/sublime.py
sak/tex.py
sak/text.py
sak/train.py
sak/update.py
sak/url.py
sak.egg-info/PKG-INFO
sak.egg-info/SOURCES.txt
sak.egg-info/dependency_links.txt
sak.egg-info/requires.txt
sak.egg-info/top_level.txt
sak/test/do.py