Metadata-Version: 1.0
Name: sak
Version: 0.5.0
Summary: Swiss Army Knife
Home-page: https://github.com/aureooms/sak
Author: aureooms
Author-email: aurelien.ooms@gmail.com
License: LICENSE
Platform: UNKNOWN
